inpt/__init__.py
inpt/inpt.py
inpt-0.0.5.dist-info/LICENSE
inpt-0.0.5.dist-info/METADATA
inpt-0.0.5.dist-info/WHEEL
inpt-0.0.5.dist-info/top_level.txt
inpt-0.0.5.dist-info/RECORD
