Metadata-Version: 2.1
Name: inpt
Version: 0.0.5
Summary: To help you make inputs of different types in a more convenient manner
Home-page: https://github.com/firdauskotp/inpt
Author: firdauskotp
Author-email: firdauskotp@gmail.com
Project-URL: Bug Tracker, https://github.com/firdauskotp/inpt/issues
Classifier: Programming Language :: Python :: 3
Classifier: License :: OSI Approved :: MIT License
Classifier: Operating System :: OS Independent
Requires-Python: >=3.5
License-File: LICENSE
